tomlize/__init__.py
tomlize/__main__.py
tomlize/cli.py
tomlize/converter.py
tomlize/exceptions.py
tomlize/main.py
tomlize/merger.py
tomlize/setup_py/__init__.py
tomlize/setup_py/fields_mapping.py
tomlize/setup_py/reader.py
tomlize/setup_py/remover.py
tomlize/setup_py/transformer.py
tomlize-0.2.0.dist-info/METADATA
tomlize-0.2.0.dist-info/WHEEL
tomlize-0.2.0.dist-info/entry_points.txt
tomlize-0.2.0.dist-info/top_level.txt
tomlize-0.2.0.dist-info/RECORD
