Metadata-Version: 2.1
Name: tomlize
Version: 0.2.0
Summary: Move all your configuration to pyproject.toml
Author-email: Mario Corchero <mariocj89@gmail.com>
Project-URL: Code, https://github.com/mariocj89/tomlize
Project-URL: Issue tracker, https://github.com/mariocj89/tomlize/issues
Project-URL: Download, https://pypi.org/project/tomlize/#files
Keywords: pyproject,configuration,python,tool
Classifier: Programming Language :: Python :: 3.8
Classifier: Programming Language :: Python :: 3.9
Classifier: Programming Language :: Python :: 3.10
Classifier: Programming Language :: Python :: 3.11
Requires-Python: >=3.8
Requires-Dist: tomlkit
Requires-Dist: coloredlogs
Requires-Dist: packaging
